artof_utils/__init__.py
artof_utils/implement.py
artof_utils/paths.py
artof_utils/redis.py
artof_utils/redis_instance.py
artof_utils/robot.py
artof_utils/shapefile.py
artof_utils/singleton.py
artof_utils/helpers/__init__.py
artof_utils/helpers/array.py
artof_utils/helpers/hardware.py
artof_utils/helpers/polygon.py
artof_utils/helpers/shape.py
artof_utils/helpers/task.py
artof_utils/helpers/traject.py
artof_utils/schemas/__init__.py
artof_utils/schemas/affine.py
artof_utils/schemas/field.py
artof_utils/schemas/hitches.py
artof_utils/schemas/implement.py
artof_utils/schemas/navigation.py
artof_utils/schemas/settings.py
artof_utils/schemas/sim.py
artof_utils/schemas/state.py
artof_utils/schemas/task.py
artof_utils-0.0.2.dist-info/licenses/LICENSE
tests/__init__.py
tests/test_field.py
tests/test_helpers_array.py
tests/test_helpers_hardware.py
tests/test_helpers_task.py
tests/test_helpers_traject.py
tests/test_implements.py
tests/test_redis.py
tests/test_robot.py
tests/test_shapefile.py
tests/test_state.py
tests/visual_multipolygon_buffer.py
tests/visual_polygon_buffer.py
tests/visual_support.py
tests/visual_traject_add.py
tests/visual_traject_extend.py
tests/visual_traject_operations.py
tests/visual_traject_remove.py
tests/visual_traject_rows.py
tests/visual_traject_shift.py
artof_utils-0.0.2.dist-info/METADATA
artof_utils-0.0.2.dist-info/WHEEL
artof_utils-0.0.2.dist-info/top_level.txt
artof_utils-0.0.2.dist-info/RECORD
