Metadata-Version: 2.4
Name: artof_utils
Version: 0.0.2
Summary: The ARTOF framework utils
Author-email: Axel Willekens <axel.willekens@ilvo.vlaanderen.be>
Classifier: Programming Language :: Python :: 3
Classifier: Operating System :: OS Independent
Requires-Python: >=3.7
License-File: LICENSE
Requires-Dist: redis>=4.6.0
Requires-Dist: numpy>=1.25.1
Requires-Dist: scipy>=1.11.1
Requires-Dist: toml>=0.10.2
Requires-Dist: requests>=2.31.0
Requires-Dist: pydantic>=2.0.0
Requires-Dist: python-dotenv>=1.0.0
Requires-Dist: geopandas>=0.14.1
Requires-Dist: shapely>=2.0.2
Requires-Dist: pyproj>=3.6.1
Requires-Dist: pyarrow>=15.0.0
Requires-Dist: pandas>=2.2.0
Dynamic: license-file
